moniotclient/IotMqttClient.py
moniotclient/__init__.py
railmonfiware/IotMqttClient.py
railmonfiware/__init__.py
railmoniotagent/IotMqttClient.py
railmoniotagent/__init__.py
railmoniotagent-1.5.dist-info/LICENSE.txt
railmoniotagent-1.5.dist-info/METADATA
railmoniotagent-1.5.dist-info/WHEEL
railmoniotagent-1.5.dist-info/top_level.txt
railmoniotagent-1.5.dist-info/RECORD
