Metadata-Version: 2.1
Name: railmoniotagent
Version: 1.5
Summary: Sending big files with mqtt feature was added
Home-page: http://github.com/ayhant
Author: Ayhan Taşyurt
Author-email: ayhantsyurt@gmail.com
License: MIT
Platform: UNKNOWN
Requires-Dist: paho-mqtt
